mymcdm/__init__.py
mymcdm/cli.py
mymcdm/inout.py
mymcdm/main.py
mymcdm/methods/__init__.py
mymcdm/methods/ahp.py
mymcdm/methods/electre.py
mymcdm/methods/topsis.py
mymcdm/methods/vikor.py
mymcdm/methods/wpm.py
mymcdm/methods/wsm.py
mymcdm/normalization/__init__.py
mymcdm/normalization/linear.py
mymcdm/normalization/logarithmic.py
mymcdm/normalization/max.py
mymcdm/normalization/max_min.py
mymcdm/normalization/sum.py
mymcdm/normalization/vector.py
mymcdm/utils/__init__.py
mymcdm/utils/framing.py
mymcdm/utils/misc.py
mymcdm/utils/types.py
mymcdm/utils/validation.py
mymcdm/weighting/__init__.py
mymcdm/weighting/entropy.py
mymcdm/weighting/mean.py
mymcdm/weighting/pairwise.py
mymcdm/weighting/point_alocation.py
mymcdm/weighting/statistical.py
mymcdm-1.1.1.dist-info/METADATA
mymcdm-1.1.1.dist-info/WHEEL
mymcdm-1.1.1.dist-info/entry_points.txt
mymcdm-1.1.1.dist-info/top_level.txt
mymcdm-1.1.1.dist-info/RECORD
