Metadata-Version: 2.1
Name: mymcdm
Version: 1.1.1
Summary: Practical part of my bachelor thesis
Author: Marek Brodacký
Author-email: brodackym@gmail.com
Keywords: mcdm,madm,decision-making,normalization methods
Classifier: Programming Language :: Python :: 3.11
Classifier: Intended Audience :: Science/Research
Classifier: Natural Language :: English
Classifier: Typing :: Typed
Requires-Dist: numpy (>=1.24.2)
Requires-Dist: pandas (>=1.5.3)
